MANIFEST.in
README.md
setup.py
surrkick/__init__.py
surrkick/surrkick.py
surrkick.egg-info/PKG-INFO
surrkick.egg-info/SOURCES.txt
surrkick.egg-info/dependency_links.txt
surrkick.egg-info/not-zip-safe
surrkick.egg-info/requires.txt
surrkick.egg-info/top_level.txt
surrkick/nr_comparison_data/RITdata.txt
surrkick/nr_comparison_data/RITkicks.txt
surrkick/nr_comparison_data/nr_kicks_t100.dat
surrkick/nr_comparison_data/nr_kicks_t4500.dat
surrkick/nr_comparison_data/profile_case_id_0021/params.json
surrkick/nr_comparison_data/profile_case_id_0021/radiated_p.dat
surrkick/nr_comparison_data/profile_case_id_0283/params.json
surrkick/nr_comparison_data/profile_case_id_0283/radiated_p.dat
surrkick/nr_comparison_data/profile_case_id_0353/params.json
surrkick/nr_comparison_data/profile_case_id_0353/radiated_p.dat
surrkick/nr_comparison_data/profile_case_id_3144/params.json
surrkick/nr_comparison_data/profile_case_id_3144/radiated_p.dat